{"12650":["TR","12650","Dalbasan","Bing\u00f6l","12","Yayladere","8631554","","","39.1559","39.9625","4"],"12830":["TR","12830","G\u00fczg\u00fcl\u00fc","Bing\u00f6l","12","Yedisu","8631555","","","39.4413","40.4935","3"],"12700":["TR","12700","S\u00fckyan","Bing\u00f6l","12","Solhan","8631557","","","38.8789","41.0073","3"],"12500":["TR","12500","Sarmakaya","Bing\u00f6l","12","Gen\u00e7","8631559","","","38.7272","40.9431","4"],"12800":["TR","12800","Topraklik","Bing\u00f6l","12","Ki\u011fi","8631560","","","39.3862","40.3356","4"],"12000":["TR","12000","\u00c7i\u00e7ekdere","Bing\u00f6l","12","Bing\u00f6l","","","","38.9551","40.4474","4"],"12300":["TR","12300","Sancak","Bing\u00f6l","12","Bing\u00f6l","","","","39.0967","40.3886","4"],"12400":["TR","12400","Dallitepe","Bing\u00f6l","12","Bing\u00f6l","","","","39.031","40.6069","4"],"12600":["TR","12600","Ayvad\u00fcz\u00fc","Bing\u00f6l","12","Adakli","","","","39.2513","40.5813","4"],"12900":["TR","12900","Su\u00e7ati","Bing\u00f6l","12","Karliova","","","","39.3921","40.922","4"]}