{"28950":["TR","28950","\u00c7alk\u00f6y","Giresun","28","Dereli","7911037","","","40.6833","38.5333","4"],"28520":["TR","28520","D\u00fcz\u00e7ukur","Giresun","28","G\u00fcce","8631620","","","40.7945","38.8062","4"],"28510":["TR","28510","Oyraca","Giresun","28","Do\u011fankent","8631621","","","40.827","38.903","4"],"28800":["TR","28800","Akharman","Giresun","28","G\u00f6rele","8631622","","","40.9547","38.9656","3"],"28820":["TR","28820","\u00c7avu\u015flu","Giresun","28","G\u00f6rele","8631622","","","41.039","39.0773","4"],"28850":["TR","28850","Kemerli","Giresun","28","Eynesil","8631623","","","40.9951","39.1174","4"],"28600":["TR","28600","Espiye","Giresun","28","Espiye","8631624","","","40.9479","38.7115","4"],"28400":["TR","28400","G\u00fczelyurt","Giresun","28","\u015eebinkarahisar","8631626","","","40.292","38.446","3"],"28300":["TR","28300","Bulancak","Giresun","28","Bulancak","8631628","","","40.9372","38.2291","4"],"28310":["TR","28310","Burunucu","Giresun","28","Bulancak","8631628","","","40.9352","38.2931","4"],"28340":["TR","28340","G\u00fcneyk\u00f6y","Giresun","28","Piraziz","8631629","","","40.8885","38.0692","4"],"28700":["TR","28700","Hacihasan","Giresun","28","Alucra","8631630","","","40.2704","38.9011","4"],"28710":["TR","28710","Kayacik","Giresun","28","\u00c7amoluk","8631631","","","40.2075","38.8094","4"],"28500":["TR","28500","Hala\u00e7li","Giresun","28","Tirebolu","9540843","","","40.9363","38.8379","3"],"28900":["TR","28900","Halkali","Giresun","28","Ke\u015fap","9541080","","","40.8231","38.5481","4"],"28000":["TR","28000","Ergence","Giresun","28","Giresun","","","","40.8407","38.3438","4"],"28030":["TR","28030","Duro\u011flu","Giresun","28","Giresun","","","","40.8431","38.4706","4"],"28100":["TR","28100","Aksu","Giresun","28","Giresun","","","","40.5659","38.2036","4"],"28200":["TR","28200","Batlama","Giresun","28","Giresun","","","","40.7102","38.6139","1"],"28610":["TR","28610","\u00d6merli","Giresun","28","Ya\u011flidere","","","","40.8919","38.6171","4"],"28810":["TR","28810","Kahraman","Giresun","28","\u00c7anak\u00e7i","","","","40.8167","39.1167","4"]}