{"69400":["TR","69400","\u00c7imentepe","Bayburt","77","Demir\u00f6z\u00fc","8631613","","","40.1026","39.7065","4"],"69450":["TR","69450","G\u00f6k\u00e7edere","Bayburt","77","Demir\u00f6z\u00fc","8631613","","","40.1066","39.8636","1"],"69000":["TR","69000","Konursu","Bayburt","77","Bayburt","","","","40.3948","40.2609","4"],"69300":["TR","69300","Arpali","Bayburt","77","Bayburt","","","","40.3669","40.1044","4"],"69500":["TR","69500","Sirata\u015flar","Bayburt","77","Aydintepe","","","","40.4705","40.2652","4"]}